pyrite/attract/__init__.py
pyrite/attract/config.py
pyrite/gui/__init__.py
pyrite/gui/gui01x0_tktraits.py
pyrite/gui/gui02x0_tktypes.py
pyrite/gui/gui03x0_tktools.py
pyrite/gui/gui04x1_tkliterals.py
pyrite/gui/gui05x1_tkext.py
pyrite/gui/gui06x2_tktraits.py
pyrite/gui/gui07x2_tktools.py
pyrite/gui/gui08x2_tktypes.py
pyrite/gui/gui11x0_wintraits.py
pyrite/gui/gui12x0_wintypes.py
pyrite/gui/gui13x0_winapi.py
pyrite/gui/gui14x1_wintraits.py
pyrite/gui/gui15x1_wintypes.py
pyrite/gui/gui16x1_winapi.py
pyrite/gui/gui17x2_wintools.py
pyrite/gui/guiX2x3_tools.py
pyrite/gui/guiX3x3_types.py
pyrite/gui/guiXXx4_gui.py
pyrite/helpers/__init__.py
pyrite/monolith/__init__.py
pyrite/monolith/pyrite_monolith.py
pyrite/monolith/layers/__init__.py
pyrite/monolith/layers/l01x0_common_layers.py
pyrite/monolith/layers/l02x1_tk_layers.py
pyrite/monolith/layers/l03x1_textual_layers.py
pyrite/monolith/layers/textual.py
pyrite/monolith/layers/tk.py
pyrite/smarts/__init__.py
pyrite/terminal/__init__.py
pyrite/terminal/ansi.py
pyrite/tools/shell/attract_locate.py
pyrite/tools/shell/pyrite_shell.py
pyrite/tools/shell/window_rake.py
pyrite_mx-0.1.3.dist-info/licenses/LICENSE
pyrite_mx-0.1.3.dist-info/METADATA
pyrite_mx-0.1.3.dist-info/WHEEL
pyrite_mx-0.1.3.dist-info/entry_points.txt
pyrite_mx-0.1.3.dist-info/top_level.txt
pyrite_mx-0.1.3.dist-info/RECORD
